Scrapinger/Library/browserContainer.py
Scrapinger/Library/scrapingConfig.py
Scrapinger/Library/scrapingConfigre.py
Scrapinger/Library/scrapingerException.py
Scrapinger/Library/scrapingerGlobals.py
Scrapinger/Library/webBrowserController.py
Scrapinger/Library/webDriverController.py
Scrapinger/Library/Base/baseBrowserContainer.py
Scrapinger/Library/Base/baseWebBrowserController.py
Scrapinger-1.0.45.dist-info/METADATA
Scrapinger-1.0.45.dist-info/WHEEL
Scrapinger-1.0.45.dist-info/top_level.txt
Scrapinger-1.0.45.dist-info/RECORD
