Metadata-Version: 2.1
Name: Scrapinger
Version: 1.0.45
Summary: Scraping Support
Home-page: https://github.com/kaioman/Scrapinger.git
Author: Unchain Works
Author-email: kajin0318@gmail.com
License: BSD-3-Clause
Keywords: Scraping,スクレイピング
Classifier: Development Status :: 5 - Production/Stable
Classifier: License :: OSI Approved :: BSD License
Classifier: Programming Language :: Python
Classifier: Programming Language :: Python :: 3
Classifier: Programming Language :: Python :: 3.4
Classifier: Programming Language :: Python :: 3.5
Classifier: Programming Language :: Python :: 3.6
Classifier: Programming Language :: Python :: 3.7
Classifier: Programming Language :: Python :: 3.8
Classifier: Programming Language :: Python :: 3.9
Classifier: Topic :: Database
Classifier: Topic :: Software Development :: Libraries :: Python Modules
Requires-Dist: LibHanger
Requires-Dist: bs4 ==0.0.1
Requires-Dist: selenium ==3.141.0
Requires-Dist: urllib3 ==1.26.7
Requires-Dist: lxml ==4.9.1
Requires-Dist: wheel
Requires-Dist: twine
